{"cameraMode":{"drawMode":0,"name":"Shaded","section":"Shading Mode"},"sceneLighting":true,"audioPlay":false,"sceneViewState":{"m_AlwaysRefresh":false,"showFog":true,"showSkybox":true,"showFlares":true,"showImageEffects":true,"showParticleSystems":true,"showVisualEffectGraphs":true,"m_FxEnabled":true},"in2DMode":false,"pivot":{"x":-1.088342547416687,"y":-3.6455793380737306,"z":-17.249691009521486},"rotation":{"x":-0.03501112014055252,"y":0.9649643898010254,"z":-0.18039321899414063,"w":-0.18728245794773103},"size":8.7959566116333,"orthographic":false}